jax_hpc_profiler/__init__.py
jax_hpc_profiler/create_argparse.py
jax_hpc_profiler/main.py
jax_hpc_profiler/plotting.py
jax_hpc_profiler/timer.py
jax_hpc_profiler/utils.py
jax_hpc_profiler-0.2.13.dist-info/licenses/LICENSE
jax_hpc_profiler-0.2.13.dist-info/METADATA
jax_hpc_profiler-0.2.13.dist-info/WHEEL
jax_hpc_profiler-0.2.13.dist-info/entry_points.txt
jax_hpc_profiler-0.2.13.dist-info/top_level.txt
jax_hpc_profiler-0.2.13.dist-info/RECORD
