Metadata-Version: 2.4
Name: jax_hpc_profiler
Version: 0.2.13
Summary: HPC Plotter and profiler for benchmarking data made for JAX
Author: Wassim Kabalan
License:                     GNU GENERAL PUBLIC LICENSE
Project-URL: Homepage, https://github.com/ASKabalan/jax-hpc-profiler
Keywords: jax,hpc,profiler,plotter,benchmarking
Classifier: Development Status :: 4 - Beta
Classifier: Intended Audience :: Developers
Classifier: License :: OSI Approved :: GNU General Public License v3 (GPLv3)
Classifier: Programming Language :: Python :: 3
Classifier: Programming Language :: Python :: 3.8
Classifier: Programming Language :: Python :: 3.9
Classifier: Programming Language :: Python :: 3.10
Classifier: Programming Language :: Python :: 3.11
Classifier: Programming Language :: Python :: 3.12
Classifier: Programming Language :: Python :: 3 :: Only
Requires-Python: >=3.8
License-File: LICENSE
Requires-Dist: numpy
Requires-Dist: pandas
Requires-Dist: matplotlib
Requires-Dist: seaborn
Requires-Dist: tabulate
Dynamic: license-file
